fhirgenerator/__init__.py
fhirgenerator/command_line.py
fhirgenerator/main.py
fhirgenerator/docs/__init__.py
fhirgenerator/helpers/__init__.py
fhirgenerator/helpers/helpers.py
fhirgenerator/models/__init__.py
fhirgenerator/models/usCoreSTU4/__init__.py
fhirgenerator/models/usCoreSTU4/usCorePatient.py
fhirgenerator/resources/__init__.py
fhirgenerator/resources/r4/__init__.py
fhirgenerator/resources/r4/bundle.py
fhirgenerator/resources/r4/condition.py
fhirgenerator/resources/r4/encounter.py
fhirgenerator/resources/r4/location.py
fhirgenerator/resources/r4/medicationStatement.py
fhirgenerator/resources/r4/observation.py
fhirgenerator/resources/r4/organization.py
fhirgenerator/resources/r4/patient.py
fhirgenerator/resources/r4/procedure.py
fhirgenerator/resources/uscore_r4/__init__.py
fhirgenerator/resources/uscore_r4/handleUSCore.py
fhirgenerator/resources/uscore_r4/usCoreBMIObservation.py
fhirgenerator/resources/uscore_r4/usCoreBodyHeightObservation.py
fhirgenerator/resources/uscore_r4/usCoreBodyTemperatureObservation.py
fhirgenerator/resources/uscore_r4/usCoreBodyWeightObservation.py
fhirgenerator/resources/uscore_r4/usCoreCondition.py
fhirgenerator/resources/uscore_r4/usCoreHeadCircumferenceObservation.py
fhirgenerator/resources/uscore_r4/usCoreHeartRateObservation.py
fhirgenerator/resources/uscore_r4/usCoreLabResultObservation.py
fhirgenerator/resources/uscore_r4/usCoreLocation.py
fhirgenerator/resources/uscore_r4/usCoreOrganization.py
fhirgenerator/resources/uscore_r4/usCorePatient.py
fhirgenerator/tests/__init__.py
fhirgenerator/tests/test_bundle.py
fhirgenerator/tests/test_condition.py
fhirgenerator/tests/test_encounter.py
fhirgenerator/tests/test_location.py
fhirgenerator/tests/test_main.py
fhirgenerator/tests/test_medicationStatement.py
fhirgenerator/tests/test_observation.py
fhirgenerator/tests/test_organization.py
fhirgenerator/tests/test_patient.py
fhirgenerator/tests/test_procedure.py
fhirgenerator/tests/test_usCoreBMIObservation.py
fhirgenerator-0.1.6.dist-info/LICENSE
fhirgenerator-0.1.6.dist-info/METADATA
fhirgenerator-0.1.6.dist-info/WHEEL
fhirgenerator-0.1.6.dist-info/entry_points.txt
fhirgenerator-0.1.6.dist-info/top_level.txt
fhirgenerator-0.1.6.dist-info/RECORD
