Metadata-Version: 2.1
Name: fhirgenerator
Version: 0.1.6
Summary: A package to generate FHIR Resources using a configuration file
Home-page: https://github.com/SmartChartSuite/FHIRGenerator
Author: Andrew Stevens
Author-email: andrew.stevens@gtri.gatech.edu
Project-URL: Bug Tracker, https://github.com/SmartChartSuite/FHIRGenerator/issues
Classifier: Programming Language :: Python :: 3.10
Classifier: License :: OSI Approved :: MIT License
Classifier: Operating System :: OS Independent
Requires-Python: >=3.10
License-File: LICENSE
Requires-Dist: fhir.resources (>=6.2.2)
Requires-Dist: Faker (>=13.3.4)
Requires-Dist: orjson (>=3.6.8)
